flanks/__init__.py
flanks/flanks.py
tests/__init__.py
tests/test_clustr.py
tests/vcr_clustr.py
flanks-0.0.3.dist-info/METADATA
flanks-0.0.3.dist-info/WHEEL
flanks-0.0.3.dist-info/top_level.txt
flanks-0.0.3.dist-info/RECORD
