Metadata-Version: 2.1
Name: flanks
Version: 0.0.3
Summary: Small client for FlanksAPI
Home-page: https://github.com/flanks-io/python-flanks
Author: Flanks Team
Author-email: hello@flanks.io
License: UNKNOWN
Platform: UNKNOWN
Classifier: Programming Language :: Python :: 3
Requires-Dist: requests (>=2.20) ; python_version >= "3.0"
